boneless/__init__.py
boneless/boneless.py
boneless-0.0.1.dist-info/LICENSE
boneless-0.0.1.dist-info/METADATA
boneless-0.0.1.dist-info/WHEEL
boneless-0.0.1.dist-info/top_level.txt
boneless-0.0.1.dist-info/RECORD
