Metadata-Version: 2.1
Name: boneless
Version: 0.0.1
Summary: can i get a boneless pizza
Home-page: https://github.com/jakeelkins/boneless
Author: Jake Elkins
License: MIT
Platform: UNKNOWN
Requires-Python: >=3.6
